README.md
setup.py
aviraj/__init__.py
aviraj/execute.py
aviraj.egg-info/PKG-INFO
aviraj.egg-info/SOURCES.txt
aviraj.egg-info/dependency_links.txt
aviraj.egg-info/top_level.txt