Metadata-Version: 2.1
Name: aviraj
Version: 0.1
Summary: A Dependency injection check package
Home-page: https://github.com/akshukatkar/dependecy
Author: Akshay Katkar
Author-email: akshukatkar@gmail.com
License: UNKNOWN
Platform: UNKNOWN
Classifier: Programming Language :: Python :: 3
Classifier: License :: OSI Approved :: MIT License
Classifier: Operating System :: OS Independent
